{
  "total": 1,
  "tools inspection": {
    "Code Inspection": 1
  },
  "attributes": {
    "vcs": {
      "sarifIdea": {
        "repositoryUri": "https://github.com/JavierSegoviaCordoba/mokoki",
        "revisionId": "1ee3e9092be37d29236b732807644866dbc929b9",
        "branch": "main"
      }
    },
    "deviceId": "200820300000000-818f-e2ab-5c7b-bb2195b3536f",
    "jobUrl": "https://github.com/JavierSegoviaCordoba/mokoki/actions/runs/3244956963",
    "repoUrl": "https://github.com/JavierSegoviaCordoba/mokoki"
  }
}